augmentimg/__init__.py
augmentimg/main.py
augmentimg-1.2.4.dist-info/METADATA
augmentimg-1.2.4.dist-info/WHEEL
augmentimg-1.2.4.dist-info/entry_points.txt
augmentimg-1.2.4.dist-info/top_level.txt
augmentimg-1.2.4.dist-info/RECORD
