Metadata-Version: 2.1
Name: augmentimg
Version: 1.2.4
Summary: A simple no-code tool to augment Images and Annotations
Classifier: Development Status :: 5 - Production/Stable
Classifier: Programming Language :: Python :: 3
Classifier: License :: OSI Approved :: MIT License
Classifier: Operating System :: OS Independent
Requires-Python: >=3.7
Requires-Dist: PyQt5 >=5.15
Requires-Dist: albumentations >=1.2.0
Requires-Dist: opencv-python >=4.5.0
Requires-Dist: numpy >=1.21.0
